{"is_source_file": false, "format": "", "description": "", "external_files": [], "external_methods": [], "published": [], "classes": [], "methods": [], "calls": [], "search-terms": [], "state": 2, "file_id": 5, "knowledge_revision": 17, "git_revision": "b971fce607938006ad9a7e306cc9a4c5529c4f81", "hash": "3c1768b77216592a4081b38e1e50898f", "format-version": 4, "code-base-name": "servicehub_frontend", "filename": "servicehub_frontend/src/app/globals.css", "revision_history": [{"17": "b971fce607938006ad9a7e306cc9a4c5529c4f81"}]}